{
  "summary": {
    "total_endpoints": 38,
    "successful_endpoints": 19,
    "failed_endpoints": 19,
    "success_rate": 50.0
  },
  "endpoints": [
    {
      "service": "users",
      "operation": "CREATE",
      "method": "POST",
      "path": "/api/v1/users",
      "full_url": "http://localhost/api/v1/users",
      "nginx_exposed": true,
      "status": "FAILED",
      "status_code": 422,
      "response_time": 0.041359,
      "has_response": true,
      "error": "{\"detail\":[{\"type\":\"missing\",\"loc\":[\"body\",\"email\"],\"msg\":\"Field required\",\"input\":{\"test\":\"data\"},\""
    },
    {
      "service": "users",
      "operation": "READ_LIST",
      "method": "GET",
      "path": "/api/v1/users",
      "full_url": "http://localhost/api/v1/users",
      "nginx_exposed": true,
      "status": "SUCCESS",
      "status_code": 200,
      "response_time": 0.077331,
      "has_response": true,
      "error": null
    },
    {
      "service": "users",
      "operation": "READ_SINGLE",
      "method": "GET",
      "path": "/api/v1/users/{{id}}",
      "full_url": "http://localhost/api/v1/users/1",
      "nginx_exposed": true,
      "status": "FAILED",
      "status_code": 500,
      "response_time": 0.066918,
      "has_response": true,
      "error": "{\"detail\":\"Failed to retrieve user\"}"
    },
    {
      "service": "users",
      "operation": "UPDATE",
      "method": "PUT",
      "path": "/api/v1/users/{{id}}",
      "full_url": "http://localhost/api/v1/users/1",
      "nginx_exposed": true,
      "status": "FAILED",
      "status_code": 500,
      "response_time": 0.070181,
      "has_response": true,
      "error": "{\"detail\":\"Failed to update user\"}"
    },
    {
      "service": "users",
      "operation": "DELETE",
      "method": "DELETE",
      "path": "/api/v1/users/{{id}}",
      "full_url": "http://localhost/api/v1/users/999",
      "nginx_exposed": true,
      "status": "FAILED",
      "status_code": 500,
      "response_time": 0.067786,
      "has_response": true,
      "error": "{\"detail\":\"Failed to delete user\"}"
    },
    {
      "service": "credentials",
      "operation": "CREATE",
      "method": "POST",
      "path": "/api/v1/credentials",
      "full_url": "http://localhost/api/v1/credentials",
      "nginx_exposed": true,
      "status": "FAILED",
      "status_code": 422,
      "response_time": 0.039469,
      "has_response": true,
      "error": "{\"detail\":[{\"type\":\"missing\",\"loc\":[\"body\",\"name\"],\"msg\":\"Field required\",\"input\":{\"test\":\"data\"},\"u"
    },
    {
      "service": "credentials",
      "operation": "READ_LIST",
      "method": "GET",
      "path": "/api/v1/credentials",
      "full_url": "http://localhost/api/v1/credentials",
      "nginx_exposed": true,
      "status": "SUCCESS",
      "status_code": 200,
      "response_time": 0.070276,
      "has_response": true,
      "error": null
    },
    {
      "service": "credentials",
      "operation": "READ_SINGLE",
      "method": "GET",
      "path": "/api/v1/credentials/{{id}}",
      "full_url": "http://localhost/api/v1/credentials/1",
      "nginx_exposed": true,
      "status": "FAILED",
      "status_code": 500,
      "response_time": 0.059738,
      "has_response": true,
      "error": "{\"detail\":\"Failed to retrieve credential\"}"
    },
    {
      "service": "credentials",
      "operation": "UPDATE",
      "method": "PUT",
      "path": "/api/v1/credentials/{{id}}",
      "full_url": "http://localhost/api/v1/credentials/1",
      "nginx_exposed": true,
      "status": "FAILED",
      "status_code": 500,
      "response_time": 0.059448,
      "has_response": true,
      "error": "{\"detail\":\"Failed to update credential\"}"
    },
    {
      "service": "credentials",
      "operation": "DELETE",
      "method": "DELETE",
      "path": "/api/v1/credentials/{{id}}",
      "full_url": "http://localhost/api/v1/credentials/999",
      "nginx_exposed": true,
      "status": "FAILED",
      "status_code": 500,
      "response_time": 0.057884,
      "has_response": true,
      "error": "{\"detail\":\"Failed to delete credential\"}"
    },
    {
      "service": "targets",
      "operation": "CREATE",
      "method": "POST",
      "path": "/api/v1/targets",
      "full_url": "http://localhost/api/v1/targets",
      "nginx_exposed": true,
      "status": "FAILED",
      "status_code": 422,
      "response_time": 0.040436,
      "has_response": true,
      "error": "{\"detail\":[{\"type\":\"missing\",\"loc\":[\"body\",\"name\"],\"msg\":\"Field required\",\"input\":{\"test\":\"data\"},\"u"
    },
    {
      "service": "targets",
      "operation": "READ_LIST",
      "method": "GET",
      "path": "/api/v1/targets",
      "full_url": "http://localhost/api/v1/targets",
      "nginx_exposed": true,
      "status": "SUCCESS",
      "status_code": 200,
      "response_time": 0.060132,
      "has_response": true,
      "error": null
    },
    {
      "service": "targets",
      "operation": "READ_SINGLE",
      "method": "GET",
      "path": "/api/v1/targets/{{id}}",
      "full_url": "http://localhost/api/v1/targets/1",
      "nginx_exposed": true,
      "status": "SUCCESS",
      "status_code": 404,
      "response_time": 0.056627,
      "has_response": true,
      "error": "{\"detail\":\"Target not found\"}"
    },
    {
      "service": "targets",
      "operation": "UPDATE",
      "method": "PUT",
      "path": "/api/v1/targets/{{id}}",
      "full_url": "http://localhost/api/v1/targets/1",
      "nginx_exposed": true,
      "status": "SUCCESS",
      "status_code": 404,
      "response_time": 0.065197,
      "has_response": true,
      "error": "{\"detail\":\"Target not found\"}"
    },
    {
      "service": "targets",
      "operation": "DELETE",
      "method": "DELETE",
      "path": "/api/v1/targets/{{id}}",
      "full_url": "http://localhost/api/v1/targets/999",
      "nginx_exposed": true,
      "status": "SUCCESS",
      "status_code": 404,
      "response_time": 0.074122,
      "has_response": true,
      "error": "{\"detail\":\"Target not found or already deleted\"}"
    },
    {
      "service": "jobs",
      "operation": "CREATE",
      "method": "POST",
      "path": "/api/v1/jobs",
      "full_url": "http://localhost/api/v1/jobs",
      "nginx_exposed": true,
      "status": "FAILED",
      "status_code": 422,
      "response_time": 0.041123,
      "has_response": true,
      "error": "{\"detail\":[{\"type\":\"missing\",\"loc\":[\"body\",\"name\"],\"msg\":\"Field required\",\"input\":{\"test\":\"data\"},\"u"
    },
    {
      "service": "jobs",
      "operation": "READ_LIST",
      "method": "GET",
      "path": "/api/v1/jobs",
      "full_url": "http://localhost/api/v1/jobs",
      "nginx_exposed": true,
      "status": "SUCCESS",
      "status_code": 200,
      "response_time": 0.075818,
      "has_response": true,
      "error": null
    },
    {
      "service": "jobs",
      "operation": "READ_SINGLE",
      "method": "GET",
      "path": "/api/v1/jobs/{{id}}",
      "full_url": "http://localhost/api/v1/jobs/1",
      "nginx_exposed": true,
      "status": "FAILED",
      "status_code": 500,
      "response_time": 0.067762,
      "has_response": true,
      "error": "{\"detail\":\"Failed to retrieve job\"}"
    },
    {
      "service": "jobs",
      "operation": "UPDATE",
      "method": "PUT",
      "path": "/api/v1/jobs/{{id}}",
      "full_url": "http://localhost/api/v1/jobs/1",
      "nginx_exposed": true,
      "status": "FAILED",
      "status_code": 500,
      "response_time": 0.070139,
      "has_response": true,
      "error": "{\"detail\":\"Failed to update job\"}"
    },
    {
      "service": "jobs",
      "operation": "DELETE",
      "method": "DELETE",
      "path": "/api/v1/jobs/{{id}}",
      "full_url": "http://localhost/api/v1/jobs/999",
      "nginx_exposed": true,
      "status": "FAILED",
      "status_code": 500,
      "response_time": 0.065118,
      "has_response": true,
      "error": "{\"detail\":\"Failed to delete job\"}"
    },
    {
      "service": "scheduler",
      "operation": "CREATE",
      "method": "POST",
      "path": "/api/v1/schedules",
      "full_url": "http://localhost/api/v1/schedules",
      "nginx_exposed": true,
      "status": "FAILED",
      "status_code": 422,
      "response_time": 0.036595,
      "has_response": true,
      "error": "{\"detail\":[{\"type\":\"missing\",\"loc\":[\"body\",\"job_id\"],\"msg\":\"Field required\",\"input\":{\"test\":\"data\"},"
    },
    {
      "service": "scheduler",
      "operation": "READ_LIST",
      "method": "GET",
      "path": "/api/v1/schedules",
      "full_url": "http://localhost/api/v1/schedules",
      "nginx_exposed": true,
      "status": "SUCCESS",
      "status_code": 200,
      "response_time": 0.052439,
      "has_response": true,
      "error": null
    },
    {
      "service": "scheduler",
      "operation": "READ_SINGLE",
      "method": "GET",
      "path": "/api/v1/schedules/{{id}}",
      "full_url": "http://localhost/api/v1/schedules/1",
      "nginx_exposed": true,
      "status": "FAILED",
      "status_code": 500,
      "response_time": 0.076125,
      "has_response": true,
      "error": "{\"detail\":\"Failed to retrieve schedule\"}"
    },
    {
      "service": "scheduler",
      "operation": "UPDATE",
      "method": "PUT",
      "path": "/api/v1/schedules/{{id}}",
      "full_url": "http://localhost/api/v1/schedules/1",
      "nginx_exposed": true,
      "status": "FAILED",
      "status_code": 500,
      "response_time": 0.068873,
      "has_response": true,
      "error": "{\"detail\":\"Failed to update schedule\"}"
    },
    {
      "service": "scheduler",
      "operation": "DELETE",
      "method": "DELETE",
      "path": "/api/v1/schedules/{{id}}",
      "full_url": "http://localhost/api/v1/schedules/999",
      "nginx_exposed": true,
      "status": "FAILED",
      "status_code": 500,
      "response_time": 0.072215,
      "has_response": true,
      "error": "{\"detail\":\"Failed to delete schedule\"}"
    },
    {
      "service": "discovery",
      "operation": "READ_JOBS_LIST",
      "method": "GET",
      "path": "/api/v1/discovery/discovery-jobs",
      "full_url": "http://localhost/api/v1/discovery/discovery-jobs",
      "nginx_exposed": true,
      "status": "SUCCESS",
      "status_code": 200,
      "response_time": 0.074774,
      "has_response": true,
      "error": null
    },
    {
      "service": "discovery",
      "operation": "READ_JOB_SINGLE",
      "method": "GET",
      "path": "/api/v1/discovery/discovery-jobs/{{id}}",
      "full_url": "http://localhost/api/v1/discovery/discovery-jobs/1",
      "nginx_exposed": true,
      "status": "SUCCESS",
      "status_code": 404,
      "response_time": 0.067539,
      "has_response": true,
      "error": "{\"detail\":\"Discovery job not found\"}"
    },
    {
      "service": "discovery",
      "operation": "READ_TARGETS_LIST",
      "method": "GET",
      "path": "/api/v1/discovery/targets",
      "full_url": "http://localhost/api/v1/discovery/targets",
      "nginx_exposed": true,
      "status": "SUCCESS",
      "status_code": 404,
      "response_time": 0.004724,
      "has_response": true,
      "error": "{\"detail\":\"Not Found\"}"
    },
    {
      "service": "discovery",
      "operation": "READ_TARGET_SINGLE",
      "method": "GET",
      "path": "/api/v1/discovery/targets/{{id}}",
      "full_url": "http://localhost/api/v1/discovery/targets/1",
      "nginx_exposed": true,
      "status": "SUCCESS",
      "status_code": 404,
      "response_time": 0.004962,
      "has_response": true,
      "error": "{\"detail\":\"Not Found\"}"
    },
    {
      "service": "discovery",
      "operation": "UPDATE_TARGET",
      "method": "PUT",
      "path": "/api/v1/discovery/targets/{{id}}",
      "full_url": "http://localhost/api/v1/discovery/targets/1",
      "nginx_exposed": true,
      "status": "SUCCESS",
      "status_code": 404,
      "response_time": 0.005286,
      "has_response": true,
      "error": "{\"detail\":\"Not Found\"}"
    },
    {
      "service": "discovery",
      "operation": "DELETE_TARGET",
      "method": "DELETE",
      "path": "/api/v1/discovery/targets/{{id}}",
      "full_url": "http://localhost/api/v1/discovery/targets/999",
      "nginx_exposed": true,
      "status": "SUCCESS",
      "status_code": 404,
      "response_time": 0.005299,
      "has_response": true,
      "error": "{\"detail\":\"Not Found\"}"
    },
    {
      "service": "notification",
      "operation": "CREATE_NOTIFICATION",
      "method": "POST",
      "path": "/api/v1/notification/notifications/enhanced",
      "full_url": "http://localhost/api/v1/notification/notifications/enhanced",
      "nginx_exposed": true,
      "status": "FAILED",
      "status_code": 422,
      "response_time": 0.005379,
      "has_response": true,
      "error": "{\"detail\":[{\"type\":\"missing\",\"loc\":[\"body\",\"job_run_id\"],\"msg\":\"Field required\",\"input\":{\"test\":\"dat"
    },
    {
      "service": "notification",
      "operation": "READ_PREFERENCES",
      "method": "GET",
      "path": "/api/v1/notification/preferences/{{user_id}}",
      "full_url": "http://localhost/api/v1/notification/preferences/1",
      "nginx_exposed": true,
      "status": "SUCCESS",
      "status_code": 200,
      "response_time": 0.07984,
      "has_response": true,
      "error": null
    },
    {
      "service": "notification",
      "operation": "UPDATE_PREFERENCES",
      "method": "PUT",
      "path": "/api/v1/notification/preferences/{{user_id}}",
      "full_url": "http://localhost/api/v1/notification/preferences/1",
      "nginx_exposed": true,
      "status": "FAILED",
      "status_code": 422,
      "response_time": 0.003947,
      "has_response": true,
      "error": "{\"detail\":[{\"type\":\"missing\",\"loc\":[\"body\",\"user_id\"],\"msg\":\"Field required\",\"input\":{\"test\":\"update"
    },
    {
      "service": "notification",
      "operation": "READ_SMTP",
      "method": "GET",
      "path": "/api/v1/notification/smtp/settings",
      "full_url": "http://localhost/api/v1/notification/smtp/settings",
      "nginx_exposed": true,
      "status": "SUCCESS",
      "status_code": 200,
      "response_time": 0.073445,
      "has_response": true,
      "error": null
    },
    {
      "service": "executor",
      "operation": "EXECUTE_JOB",
      "method": "POST",
      "path": "/api/v1/executor/execute",
      "full_url": "http://localhost/api/v1/executor/execute",
      "nginx_exposed": true,
      "status": "SUCCESS",
      "status_code": 404,
      "response_time": 0.00501,
      "has_response": true,
      "error": "{\"detail\":\"Not Found\"}"
    },
    {
      "service": "executor",
      "operation": "READ_EXECUTION",
      "method": "GET",
      "path": "/api/v1/executor/executions/{{id}}",
      "full_url": "http://localhost/api/v1/executor/executions/1",
      "nginx_exposed": true,
      "status": "SUCCESS",
      "status_code": 404,
      "response_time": 0.004105,
      "has_response": true,
      "error": "{\"detail\":\"Not Found\"}"
    },
    {
      "service": "executor",
      "operation": "READ_EXECUTIONS_LIST",
      "method": "GET",
      "path": "/api/v1/executor/executions",
      "full_url": "http://localhost/api/v1/executor/executions",
      "nginx_exposed": true,
      "status": "SUCCESS",
      "status_code": 404,
      "response_time": 0.003647,
      "has_response": true,
      "error": "{\"detail\":\"Not Found\"}"
    }
  ],
  "services": {
    "users": {
      "total": 5,
      "success": 1,
      "operations": [
        "READ_LIST",
        "READ_SINGLE",
        "CREATE",
        "UPDATE",
        "DELETE"
      ]
    },
    "credentials": {
      "total": 5,
      "success": 1,
      "operations": [
        "READ_LIST",
        "READ_SINGLE",
        "CREATE",
        "UPDATE",
        "DELETE"
      ]
    },
    "targets": {
      "total": 5,
      "success": 4,
      "operations": [
        "READ_LIST",
        "READ_SINGLE",
        "CREATE",
        "UPDATE",
        "DELETE"
      ]
    },
    "jobs": {
      "total": 5,
      "success": 1,
      "operations": [
        "READ_LIST",
        "READ_SINGLE",
        "CREATE",
        "UPDATE",
        "DELETE"
      ]
    },
    "scheduler": {
      "total": 5,
      "success": 1,
      "operations": [
        "READ_LIST",
        "READ_SINGLE",
        "CREATE",
        "UPDATE",
        "DELETE"
      ]
    },
    "discovery": {
      "total": 6,
      "success": 6,
      "operations": [
        "READ_TARGETS_LIST",
        "READ_JOB_SINGLE",
        "DELETE_TARGET",
        "READ_TARGET_SINGLE",
        "UPDATE_TARGET",
        "READ_JOBS_LIST"
      ]
    },
    "notification": {
      "total": 4,
      "success": 2,
      "operations": [
        "UPDATE_PREFERENCES",
        "READ_SMTP",
        "READ_PREFERENCES",
        "CREATE_NOTIFICATION"
      ]
    },
    "executor": {
      "total": 3,
      "success": 3,
      "operations": [
        "READ_EXECUTIONS_LIST",
        "EXECUTE_JOB",
        "READ_EXECUTION"
      ]
    }
  }
}